brickproof/__init__.py
brickproof/__main__.py
brickproof/brickproof_runner.py
brickproof/cli.py
brickproof/config.py
brickproof/constants.py
brickproof/databricks.py
brickproof/orchestration.py
brickproof/utils.py
brickproof/version.py
tests/__init__.py
tests/test_cli.py
tests/test_databricks.py
tests/test_dummies.py
tests/test_orchestrator.py
tests/test_spark.py
tests/test_utils.py
brickproof-0.0.11.dist-info/METADATA
brickproof-0.0.11.dist-info/WHEEL
brickproof-0.0.11.dist-info/entry_points.txt
brickproof-0.0.11.dist-info/top_level.txt
brickproof-0.0.11.dist-info/RECORD
