Metadata-Version: 2.1
Name: brickproof
Version: 0.0.11
Summary: brickproof
Home-page: UNKNOWN
Author: Jordan-M-Young
Author-email: jordan.m.young0@gmail.com
License: UNKNOWN
Keywords: python3,databricks,unit test,test,cidd
Platform: UNKNOWN
Classifier: Programming Language :: Python :: 3
Classifier: Framework :: Pytest
Requires-Dist: tomlkit
Requires-Dist: requests
Requires-Dist: pydantic
